{"skeleton":{"hash":"5WifrDinTCZuyp9oezDEgmFSZgA","version":"3.3.05","width":253,"height":304.1087951660156},"bones":[{"name":"7ca6ef","parent":null,"rotation":0,"x":0,"y":0,"scaleX":1,"scaleY":1,"shareX":0,"shareY":0,"length":0,"inheritRotation":true,"inheritScale":true},{"name":"f8cef7","parent":"7ca6ef","rotation":0,"x":-1.4683073459309526e-6,"y":0,"scaleX":1,"scaleY":1,"shareX":0,"shareY":0,"length":0,"inheritRotation":true,"inheritScale":true},{"name":"57fa1c","parent":"f8cef7","rotation":0,"x":-6.402092933654785,"y":57.01898193359375,"scaleX":1,"scaleY":1,"shareX":0,"shareY":0,"length":0,"inheritRotation":true,"inheritScale":true},{"name":"ae4102","parent":"57fa1c","rotation":87.31201171875,"x":0.1214299201965332,"y":7.6905517578125,"scaleX":1,"scaleY":1,"shareX":0,"shareY":0,"length":53.52176284790039,"inheritRotation":true,"inheritScale":true},{"name":"94afbe","parent":"ae4102","rotation":3.310734748840332,"x":53.92481994628906,"y":-0.2323312759399414,"scaleX":1,"scaleY":1,"shareX":0,"shareY":0,"length":115.46656036376953,"inheritRotation":true,"inheritScale":true},{"name":"bf50d4","parent":"94afbe","rotation":-56.351593017578125,"x":47.78913879394531,"y":-47.52607727050781,"scaleX":1,"scaleY":1,"shareX":0,"shareY":0,"length":44.03044128417969,"inheritRotation":true,"inheritScale":true},{"name":"88215a","parent":"bf50d4","rotation":34.874359130859375,"x":44.030426025390625,"y":-7.62939453125e-6,"scaleX":1,"scaleY":1,"shareX":0,"shareY":0,"length":57.88832473754883,"inheritRotation":true,"inheritScale":true},{"name":"3311ec","parent":"ae4102","rotation":-126.3030014038086,"x":55.67218780517578,"y":-31.280370712280273,"scaleX":1,"scaleY":1,"shareX":0,"shareY":0,"length":47.49840545654297,"inheritRotation":true,"inheritScale":true},{"name":"a5b1a7","parent":"ae4102","rotation":-142.53414916992188,"x":45.208648681640625,"y":-27.07845115661621,"scaleX":1,"scaleY":1,"shareX":0,"shareY":0,"length":25.683874130249023,"inheritRotation":true,"inheritScale":true},{"name":"fa9d83","parent":"a5b1a7","rotation":-9.288653373718262,"x":25.683876037597656,"y":-1.52587890625e-5,"scaleX":1,"scaleY":1,"shareX":0,"shareY":0,"length":27.914995193481445,"inheritRotation":true,"inheritScale":true},{"name":"c4dfa4","parent":"fa9d83","rotation":-20.725610733032227,"x":27.914989471435547,"y":0,"scaleX":1,"scaleY":1,"shareX":0,"shareY":0,"length":21.169069290161133,"inheritRotation":true,"inheritScale":true},{"name":"4cda6e","parent":"ae4102","rotation":152.18814086914062,"x":38.92033386230469,"y":27.555543899536133,"scaleX":1,"scaleY":1,"shareX":0,"shareY":0,"length":24.569679260253906,"inheritRotation":true,"inheritScale":true},{"name":"8ebf44","parent":"4cda6e","rotation":2.465977668762207,"x":25.069427490234375,"y":0.29438018798828125,"scaleX":1,"scaleY":1,"shareX":0,"shareY":0,"length":25.29823875427246,"inheritRotation":true,"inheritScale":true},{"name":"1125a9","parent":"8ebf44","rotation":6.389414310455322,"x":25.29824447631836,"y":0,"scaleX":1,"scaleY":1,"shareX":0,"shareY":0,"length":19.655925750732422,"inheritRotation":true,"inheritScale":true},{"name":"5c1cd0","parent":"57fa1c","rotation":-104.47027587890625,"x":-25.266223907470703,"y":0.9388885498046875,"scaleX":1,"scaleY":1,"shareX":0,"shareY":0,"length":25.26028060913086,"inheritRotation":true,"inheritScale":true},{"name":"935a6e","parent":"57fa1c","rotation":-56.92074966430664,"x":17.339706420898438,"y":1.4648895263671875,"scaleX":1,"scaleY":1,"shareX":0,"shareY":0,"length":34.21220016479492,"inheritRotation":true,"inheritScale":true},{"name":"60947e","parent":"57fa1c","rotation":-93.36644744873047,"x":-13.168245315551758,"y":-5.110107421875,"scaleX":1,"scaleY":1,"shareX":0,"shareY":0,"length":26.872318267822266,"inheritRotation":true,"inheritScale":true},{"name":"f5980f","parent":"60947e","rotation":1.005072832107544,"x":26.87232208251953,"y":-3.814697265625e-6,"scaleX":1,"scaleY":1,"shareX":0,"shareY":0,"length":25.53264808654785,"inheritRotation":true,"inheritScale":true},{"name":"6ff11b","parent":"57fa1c","rotation":-66.86052703857422,"x":10.501716613769531,"y":-2.21710205078125,"scaleX":1,"scaleY":1,"shareX":0,"shareY":0,"length":33.46302032470703,"inheritRotation":true,"inheritScale":true},{"name":"3f68db","parent":"6ff11b","rotation":-3.3223519325256348,"x":33.46302032470703,"y":-5.7220458984375e-6,"scaleX":1,"scaleY":1,"shareX":0,"shareY":0,"length":31.030609130859375,"inheritRotation":true,"inheritScale":true},{"name":"62d472","parent":"1125a9","rotation":88.10940551757812,"x":8.987432479858398,"y":0.5370025634765625,"scaleX":1,"scaleY":1,"shareX":0,"shareY":0,"length":111.03057861328125,"inheritRotation":true,"inheritScale":true},{"name":"f64a7c","parent":"c4dfa4","rotation":100.76050567626953,"x":14.01382064819336,"y":0.08127593994140625,"scaleX":1,"scaleY":1,"shareX":0,"shareY":0,"length":112.6430435180664,"inheritRotation":true,"inheritScale":true},{"name":"dc37a6","parent":"ae4102","rotation":-126.83462524414062,"x":42.2711181640625,"y":-25.984359741210938,"scaleX":1,"scaleY":1,"shareX":0,"shareY":0,"length":39.358272552490234,"inheritRotation":true,"inheritScale":true},{"name":"c8103c","parent":"dc37a6","rotation":8.72935962677002,"x":39.3582763671875,"y":-7.62939453125e-6,"scaleX":1,"scaleY":1,"shareX":0,"shareY":0,"length":29.157546997070312,"inheritRotation":true,"inheritScale":true},{"name":"c927d8","parent":"c8103c","rotation":-17.766014099121094,"x":29.15753936767578,"y":0,"scaleX":1,"scaleY":1,"shareX":0,"shareY":0,"length":37.46186065673828,"inheritRotation":true,"inheritScale":true},{"name":"d8742a","parent":"f8cef7","rotation":0,"x":1.5486734810110647e-6,"y":0,"scaleX":1,"scaleY":1,"shareX":0,"shareY":0,"length":60,"inheritRotation":true,"inheritScale":true}],"slots":[{"name":"7ca6ef","bone":"d8742a","color":"ffffffff","attachment":"7ca6ef","blend":"normal"},{"name":"f8cef7","bone":"62d472","color":"ffffffff","attachment":"f8cef7","blend":"normal"},{"name":"57fa1c","bone":"4cda6e","color":"ffffffff","attachment":"57fa1c","blend":"normal"},{"name":"ae4102","bone":"ae4102","color":"ffffffff","attachment":"ae4102","blend":"normal"},{"name":"94afbe","bone":"60947e","color":"ffffffff","attachment":"94afbe","blend":"normal"},{"name":"bf50d4","bone":"f5980f","color":"ffffffff","attachment":"bf50d4","blend":"normal"},{"name":"88215a","bone":"57fa1c","color":"ffffffff","attachment":"88215a","blend":"normal"},{"name":"3311ec","bone":"6ff11b","color":"ffffffff","attachment":"3311ec","blend":"normal"},{"name":"a5b1a7","bone":"3f68db","color":"ffffffff","attachment":"a5b1a7","blend":"normal"},{"name":"fa9d83","bone":"94afbe","color":"ffffffff","attachment":"fa9d83","blend":"normal"},{"name":"c4dfa4","bone":"935a6e","color":"ffffffff","attachment":"c4dfa4","blend":"normal"},{"name":"4cda6e","bone":"f64a7c","color":"ffffffff","attachment":"4cda6e","blend":"normal"},{"name":"8ebf44","bone":"a5b1a7","color":"ffffffff","attachment":"8ebf44","blend":"normal"},{"name":"1125a9","bone":"94afbe","color":"ffffffff","attachment":"1125a9","blend":"normal"},{"name":"5c1cd0","bone":"3311ec","color":"ffffffff","attachment":"5c1cd0","blend":"normal"}],"path":[],"skins":{"default":{"7ca6ef":{"7ca6ef":{"type":"region","name":"LandShadow","path":"LandShadow","rotation":0,"x":-1.4256278291213675e-6,"y":0,"scaleX":2,"scaleY":2,"width":74,"height":38,"color":"ffffffff"}},"f8cef7":{"f8cef7":{"type":"region","name":"weapon1","path":"weapon1","rotation":23.535058975219727,"x":38.530845642089844,"y":1.9054126739501953,"scaleX":1,"scaleY":1,"width":137,"height":63,"color":"ffffffff"}},"57fa1c":{"57fa1c":{"type":"mesh","name":"arminnerdown","path":"arminnerdown","color":"ffffffff","uvs":[1,0.33451974391937256,1,1,0.45507633686065674,1,0.20923084020614624,1,0,1,0,0.9315758943557739,0,0.8020086288452148,0,0,0.6450513005256653,0,1,0,0.5763487815856934,0.43361425399780273,0.3385259509086609,0.7597390413284302,0.44180575013160706,0.19702766835689545,0.34625017642974854,0.20981749892234802,0.8543636798858643,0.5253031849861145,0.9013832211494446,0.485867440700531,0.4600068926811218,0.10856391489505768,0.757291316986084,0.2524507939815521,0.09676945209503174,0.6362146735191345,0.5753837823867798,0.7850792407989502,0.15953850746154785,0.3958311676979065,0.4498455226421356,0.5897226333618164,0.7113834023475647,0.6862087249755859,0.07453887164592743,0.6816306114196777,0.5570761561393738,0.8277382850646973,0.5466148257255554,0.9582245349884033,0.25630760192871094,0.8957382440567017],"triangles":[6,7,23,6,23,11,26,6,11,5,6,26,25,11,24,26,11,25,2,26,25,3,26,2,3,4,5,26,3,5,20,7,13,18,7,20,23,7,18,13,12,10,14,10,15,21,13,10,22,10,14,23,18,11,24,11,19,22,25,24,2,25,1,18,20,21,21,10,22,11,18,21,19,21,22,11,21,19,22,14,1,24,19,22,1,25,22,20,13,21,14,15,1,16,7,8,16,13,7,12,13,16,17,8,9,16,8,17,12,16,17,17,9,0,10,12,17,15,17,0,10,17,15,15,0,1],"vertices":[1,11,7.730000019073486,15.479999542236328,1,1,12,26.799999237060547,39.060001373291016,1,2,12,40.119998931884766,14.050000190734863,0.30000001192092896,13,16.290000915527344,12.3100004196167,0.699999988079071,2,12,46.130001068115234,2.759999990463257,0.30000001192092896,13,21.010000228881836,0.4300000071525574,0.699999988079071,2,12,51.2400016784668,-6.829999923706055,0.30000001192092896,13,25.020000457763672,-9.680000305175781,0.699999988079071,2,12,46.77000045776367,-9.210000038146973,0.30000001192092896,13,20.309999465942383,-11.539999961853027,0.699999988079071,2,12,38.310001373291016,-13.720000267028809,0.30000001192092896,13,11.399999618530273,-15.079999923706055,0.699999988079071,1,11,12.800000190734863,-41.880001068115234,1,1,11,-4.21999979019165,-12.979999542236328,1,1,11,-13.59000015258789,2.9100000858306885,1,2,11,25.229999542236328,0.2199999988079071,0.19999000430107117,12,0.1599999964237213,-0.07999999821186066,0.800000011920929,2,12,27.270000457763672,0.3400000035762787,0.5,13,2,0.11999999731779099,0.5,2,11,13.699999809265137,-14.6899995803833,0.800000011920929,12,-11.989999771118164,-14.479999542236328,0.20000000298023224,2,11,17.040000915527344,-18.489999771118164,0.19999000430107117,12,-8.819999694824219,-18.420000076293945,0.800000011920929,2,11,23.739999771118164,16.1200008392334,0.19999000430107117,12,-0.6399999856948853,15.859999656677246,0.800000011920929,2,11,19.989999771118164,16.739999771118164,0.800000011920929,12,-4.360000133514404,16.649999618530273,0.20000000298023224,1,11,7.579999923706055,-17.200000762939453,1,1,11,8.90999984741211,1.5199999809265137,1,2,12,25.110000610351562,-15.039999961853027,0.800000011920929,13,-1.850000023841858,-14.930000305175781,0.20000000298023224,2,12,23.139999389648438,12.09000015258789,0.800000011920929,13,-0.7900000214576721,12.260000228881836,0.20000000298023224,1,12,7.880000114440918,-20.520000457763672,1,1,12,13.449999809265137,-0.44999998807907104,1,1,12,13.359999656677246,14.899999618530273,1,2,12,28.6200008392334,-14.479999542236328,0.5,13,1.690000057220459,-14.760000228881836,0.5,2,12,26.3700008392334,12.739999771118164,0.5,13,2.490000009536743,12.539999961853027,0.5,2,12,35.150001525878906,16.799999237060547,0.30000001192092896,13,11.65999984741211,15.59000015258789,0.699999988079071,2,12,38.16999816894531,1.2999999523162842,0.30000001192092896,13,12.930000305175781,-0.12999999523162842,0.699999988079071],"hull":10}},"ae4102":{"ae4102":{"type":"mesh","name":"pifeng","path":"pifeng","color":"ffffffff","uvs":[1,0.5859392285346985,1,0.8672807216644287,1,1,0.8986207842826843,1,0,1,0,0.35125041007995605,0,0,0.3067968189716339,0,1,0,0.09812842309474945,0.13837547600269318,0.4561408758163452,0.4424531161785126,0.7277713418006897,0.6403841376304626,0.3410792350769043,0.608835756778717,0.609926164150238,0.2596646547317505,0.8679471015930176,0.4619166851043701,0.6478173732757568,0.7672029733657837,0.10831927508115768,0.5248820185661316,0.28520941734313965,0.29727262258529663,0.4836222529411316,0.11083738505840302,0.5413612127304077,0.6393644213676453,0.6121425628662109,0.5561280250549316,0.7344257831573486,0.3855951130390167,0.7759252786636353,0.896949827671051,0.8816770911216736,0.7686612010002136],"triangles":[4,15,22,4,22,3,14,8,0,11,14,0,15,11,23,23,11,0,23,0,1,22,15,23,22,23,1,3,22,1,3,1,2,14,21,8,11,21,14,15,19,11,10,13,21,19,12,10,20,10,21,20,19,10,21,13,8,11,20,21,11,19,20,12,19,15,17,18,13,10,17,13,12,16,17,10,12,17,13,18,8,18,7,8,9,6,7,17,9,7,17,7,18,5,6,9,5,9,17,16,5,17,4,5,16,4,16,12,4,12,15],"vertices":[2,23,48.86000061035156,14.520000457763672,0.25,24,14.329999923706055,19.84000015258789,0.75,2,23,61.38999938964844,-6.489999771118164,0.10000000149011612,24,32.68000030517578,3.640000104904175,0.8999999761581421,2,23,67.30000305175781,-16.40999984741211,0.10000000149011612,24,41.33000183105469,-3.990000009536743,0.8999999761581421,2,23,59.290000915527344,-21.190000534057617,0.10000000149011612,24,35.15999984741211,-10.979999542236328,0.8999999761581421,1,3,-31.81999969482422,-17.219999313354492,1,1,3,24.549999237060547,-14.569999694824219,1,1,3,55.06999969482422,-13.140000343322754,1,1,3,56.38999938964844,-41.33000183105469,1,1,3,59.38999938964844,-105.04000091552734,1,1,3,43.470001220703125,-22.719999313354492,1,3,3,18.59000015258789,-56.86000061035156,0.10000000149011612,22,38.90999984741211,-0.4300000071525574,0.44999998807907104,23,-0.5,-0.36000001430511475,0.44999998807907104,2,23,29.770000457763672,-2.359999895095825,0.5,24,1.2999999523162842,-2.059999942779541,0.5,3,3,3.630000114440918,-46.970001220703125,0.10000000149011612,22,39.95000076293945,-18.329999923706055,0.44999998807907104,23,-2.190000057220459,-18.209999084472656,0.44999998807907104,3,3,35.13999938964844,-70.25,0.10000000149011612,22,39.70000076293945,20.829999923706055,0.44999998807907104,23,3.5,20.530000686645508,0.44999998807907104,2,23,32.900001525878906,17.56999969482422,0.5,24,-1.7899999618530273,17.8799991607666,0.5,2,23,29.100000381469727,-15.600000381469727,0.5,24,4.710000038146973,-14.869999885559082,0.5,2,3,9.920000076293945,-25.229999542236328,0.30000001192092896,22,18.790000915527344,-26.329999923706055,0.699999988079071,2,3,30.469999313354492,-40.560001373291016,0.30000001192092896,22,18.739999771118164,-0.699999988079071,0.699999988079071,2,3,47.529998779296875,-58.029998779296875,0.30000001192092896,22,22.5,23.420000076293945,0.699999988079071,3,22,55.86000061035156,-8.65999984741211,0.15000000596046448,23,14.989999771118164,-11.0600004196167,0.699999988079071,24,-10.100000381469727,-14.850000381469727,0.15000000596046448,3,22,56.27000045776367,1.059999942779541,0.15000000596046448,23,16.8799991607666,-1.5099999904632568,0.699999988079071,24,-11.220000267028809,-5.179999828338623,0.15000000596046448,3,22,55.5099983215332,19.670000076293945,0.15000000596046448,23,18.950000762939453,16.989999771118164,0.699999988079071,24,-14.899999618530273,13.0600004196167,0.15000000596046448,2,23,45,-19.260000228881836,0.25,24,20.969999313354492,-13.510000228881836,0.75,2,23,47.650001525878906,-4.699999809265137,0.25,24,19.040000915527344,1.159999966621399,0.75],"hull":9}},"94afbe":{"94afbe":{"type":"region","name":"leginnerup","path":"leginnerup","rotation":93.3664321899414,"x":8.227149963378906,"y":1.4860782623291016,"scaleX":1,"scaleY":1,"width":28,"height":49,"color":"ffffffff"}},"bf50d4":{"bf50d4":{"type":"region","name":"leginnerdown","path":"leginnerdown","rotation":92.36135864257812,"x":7.881856918334961,"y":2.405179977416992,"scaleX":1,"scaleY":1,"width":25,"height":34,"color":"ffffffff"}},"88215a":{"88215a":{"type":"mesh","name":"body","path":"body","color":"ffffffff","uvs":[1,0.13088586926460266,1,0.3593485951423645,1,1,0.5839593410491943,1,0.1932089626789093,1,0.11071833968162537,1,0,1,0,0.3755708336830139,0,0.1944228559732437,0,0,0.2684652507305145,0,0.6259133219718933,0,1,0,0.3378964364528656,0.7046799659729004,0.7366718053817749,0.6799489855766296,0.7786258459091187,0.8381155729293823,0.1526721864938736,0.7042823433876038,0.051982589066028595,0.8178377151489258,0.3221663236618042,0.8354119062423706,0.10232746601104736,0.5621263384819031,0.3557295501232147,0.5634781122207642,0.8759592771530151,0.5513115525245667,0.3204881548881531,0.37557080388069153,0.22316667437553406,0.7044336795806885,0.25795507431030273,0.8853930234909058,0.16510622203350067,0.8549115061759949],"triangles":[6,7,17,25,5,17,5,6,17,5,25,4,11,12,0,8,9,10,22,11,0,22,10,11,1,22,0,8,10,22,7,8,22,21,22,1,19,7,22,20,22,21,19,22,20,14,20,21,20,23,19,17,7,19,21,1,2,23,16,19,13,23,20,13,20,14,17,19,16,18,23,13,15,14,21,18,13,14,15,18,14,25,16,23,24,25,23,18,24,23,3,18,15,24,18,3,4,24,3,15,21,2,3,15,2,17,16,25,4,25,24],"vertices":[1,3,65.29000091552734,-41.689998626708984,1,1,3,40.63999938964844,-42.849998474121094,1,1,2,44.83000183105469,-22.90999984741211,1,1,2,8.630000114440918,-22.90999984741211,1,2,2,-25.350000381469727,-22.90999984741211,0.30000001192092896,14,23.110000610351562,5.860000133514404,0.699999988079071,2,2,-32.529998779296875,-22.90999984741211,0.30000001192092896,14,24.899999618530273,-1.0700000524520874,0.699999988079071,2,2,-42.15999984741211,-22.90999984741211,0.30000001192092896,14,27.309999465942383,-10.399999618530273,0.699999988079071,1,3,34.810001373291016,43.970001220703125,1,1,3,54.349998474121094,44.880001068115234,1,1,3,75.33000183105469,45.869998931884766,1,1,3,76.41999816894531,22.540000915527344,1,1,3,77.87999725341797,-8.520000457763672,1,1,3,79.41000366210938,-41.029998779296875,1,2,2,-12.770000457763672,8.979999542236328,0.800000011920929,3,0.6800000071525574,12.930000305175781,0.20000000298023224,2,2,21.920000076293945,11.649999618530273,0.800000011920929,3,4.980000019073486,-21.59000015258789,0.20000000298023224,1,2,25.56999969482422,-5.420000076293945,1,2,2,-28.8799991607666,9.020000457763672,0.800000011920929,3,-0.019999999552965164,29.030000686645508,0.20000000298023224,2,2,-37.63999938964844,-3.2300000190734863,0.30000001192092896,14,7.130000114440918,-10.9399995803833,0.699999988079071,1,2,-14.130000114440918,-5.130000114440918,1,2,2,-33.2599983215332,24.3799991607666,0.20000000298023224,3,15.100000381469727,34.130001068115234,0.800000011920929,2,2,-11.210000038146973,24.229999542236328,0.20000000298023224,3,15.989999771118164,12.100000381469727,0.800000011920929,2,2,34.040000915527344,25.540000915527344,0.20000000298023224,3,19.420000076293945,-33.040000915527344,0.800000011920929,1,3,36.119998931884766,16.110000610351562,1,2,2,-22.75,9.010000228881836,0.800000011920929,3,0.23999999463558197,22.90999984741211,0.20000000298023224,1,2,-19.719999313354492,-10.529999732971191,1,3,2,-27.799999237060547,-7.239999771118164,0.30000001192092896,3,-16.219999313354492,27.190000534057617,9.999999747378752e-6,14,8.550000190734863,-0.4099999964237213,0.6999800205230713],"hull":13}},"3311ec":{"3311ec":{"type":"region","name":"legoutup","path":"legoutup","rotation":66.86051177978516,"x":21.31965446472168,"y":-2.770444869995117,"scaleX":1,"scaleY":1,"width":37,"height":42,"color":"ffffffff"}},"a5b1a7":{"a5b1a7":{"type":"region","name":"legoutdown","path":"legoutdown","rotation":70.18286895751953,"x":9.35770034790039,"y":-4.774742126464844,"scaleX":1,"scaleY":1,"width":33,"height":41,"color":"ffffffff"},"935a6e":{"type":"region","name":"legoutdown","path":"legoutdown","rotation":118.81920623779297,"x":9.774581909179688,"y":2.877166748046875,"scaleX":-1,"scaleY":1,"width":33,"height":41,"color":"ffffffff"}},"fa9d83":{"fa9d83":{"type":"region","name":"face","path":"face","rotation":-90.62274932861328,"x":63.92729187011719,"y":-11.145212173461914,"scaleX":1,"scaleY":1,"width":169,"height":167,"color":"ffffffff"}},"c4dfa4":{"c4dfa4":{"type":"region","name":"yaojia1","path":"yaojia1","rotation":56.92074203491211,"x":8.670215606689453,"y":-3.866424560546875,"scaleX":1,"scaleY":1,"width":34,"height":38,"color":"ffffffff"}},"4cda6e":{"4cda6e":{"type":"region","name":"weapon","path":"weapon","rotation":-15.524102210998535,"x":38.472686767578125,"y":-2.111330032348633,"scaleX":1,"scaleY":1,"width":146,"height":47,"color":"ffffffff"}},"8ebf44":{"8ebf44":{"type":"mesh","name":"handout","path":"handout","color":"ffffffff","uvs":[1,0.7396180629730225,1,0.8705757260322571,1,1,0.750201940536499,1,0.43534785509109497,1,0,1,0,0.2510846257209778,0,0,0.3826136291027069,0,1,0,0.4155471920967102,0.315071165561676,0.6830970048904419,0.6600702404975891,0.38726678490638733,0.6957724094390869,0.9068535566329956,0.6606957912445068,0.33298155665397644,0.7425411343574524,0.6959168910980225,0.7259771823883057,0.33918529748916626,0.8705757856369019,0.7362428903579712,0.8705757260322571,0.20114615559577942,0.5044153928756714,0.725385844707489,0.23841813206672668,0.15926888585090637,0.44400519132614136,0.6648966670036316,0.19457238912582397,0.49893906712532043,0.058163486421108246,0.23837009072303772,0.1546240597963333,0.2724922299385071,0.5916327834129333,0.5656323432922363,0.4883516728878021,0.9084046483039856,0.4094293713569641],"triangles":[5,14,16,5,16,4,15,11,13,15,13,0,14,11,15,1,17,15,1,15,0,16,14,15,16,15,17,4,16,17,3,17,1,4,17,3,3,1,2,14,12,11,9,0,26,5,24,14,11,25,26,12,24,25,12,25,11,25,10,19,25,19,26,18,10,25,24,18,25,13,11,26,14,24,12,13,26,0,22,8,9,23,7,8,23,8,22,21,22,9,6,7,23,10,23,22,10,22,21,10,21,19,20,6,23,20,23,10,18,20,10,5,6,20,19,21,9,26,19,9,5,20,18,5,18,24],"vertices":[2,9,40.959999084472656,11.369999885559082,0.30000001192092896,10,8.180000305175781,15.25,0.699999988079071,2,9,50.18000030517578,6.96999979019165,0.30000001192092896,10,18.360000610351562,14.399999618530273,0.699999988079071,2,9,59.290000915527344,2.619999885559082,0.30000001192092896,10,28.420000076293945,13.5600004196167,0.699999988079071,2,9,54.02000045776367,-8.40999984741211,0.30000001192092896,10,27.399999618530273,1.3600000143051147,0.699999988079071,2,9,47.38999938964844,-22.34000015258789,0.30000001192092896,10,26.1200008392334,-14,0.699999988079071,1,8,56.66999816894531,-47.220001220703125,1,1,8,8.6899995803833,-13.899999618530273,1,1,8,-7.380000114440918,-2.7300000190734863,1,1,8,3.299999952316284,12.65999984741211,1,1,8,20.559999465942383,37.5099983215332,1,2,8,24.40999984741211,-0.019999999552965164,0.5,9,-1.25,-0.23000000417232513,0.5,2,9,28.68000030517578,0.019999999552965164,0.5,10,0.699999988079071,0.28999999165534973,0.5,2,9,24.950000762939453,-14.25,0.5,10,2.2699999809265137,-14.380000114440918,0.5,2,9,33.439998626708984,9.890000343322754,0.5,10,1.659999966621399,11.210000038146973,0.5,2,9,27.100000381469727,-18.229999542236328,0.30000001192092896,10,5.690000057220459,-17.329999923706055,0.699999988079071,2,9,33.59000015258789,-1.6200000047683716,0.30000001192092896,10,5.880000114440918,0.49000000953674316,0.699999988079071,2,9,36.25,-22.25,0.30000001192092896,10,15.670000076293945,-17.860000610351562,0.699999988079071,2,9,44.619998931884766,-4.690000057220459,0.30000001192092896,10,17.280000686645508,1.5199999809265137,0.699999988079071,2,8,30.549999237060547,-17.06999969482422,0.5,9,7.550000190734863,-16.059999465942383,0.5,2,8,28.15999984741211,15.850000381469727,0.5,9,-0.10999999940395355,16.040000915527344,0.5,2,8,25.5,-16.06999969482422,0.800000011920929,9,2.4200000762939453,-15.890000343322754,0.20000000298023224,2,8,23.65999984741211,15.369999885559082,0.800000011920929,9,-4.46999979019165,14.84000015258789,0.20000000298023224,1,8,10.279999732971191,14.760000228881836,1,1,8,9.180000305175781,-0.009999999776482582,1,1,9,15.199999809265137,-15.84000015258789,1,1,9,14.109999656677246,0.5899999737739563,1,1,9,15.779999732971191,18.399999618530273,1],"hull":10}},"1125a9":{"1125a9":{"type":"mesh","name":"toushi","path":"toushi","color":"ffffffff","uvs":[1,0.3339473307132721,1,0.7953055500984192,1,1,0.2714152932167053,1,0,1,0,0.7809221744537354,0,0,0.816865086555481,0,1,0,0.27950721979141235,0.7228251695632935,0.2633233964443207,0.8304755687713623,0.37863337993621826,0.8680676221847534,0.6995320916175842,0.5936747789382935,0.37180855870246887,0.5389953851699829,0.5128179788589478,0.6950346231460571,0.6853711605072021,0.9302955865859985,0.5579230785369873,0.41254904866218567,0.7136930227279663,0.2587629556655884,0.8816006183624268,0.3100249469280243],"triangles":[16,6,17,17,6,7,12,18,0,12,17,18,18,8,0,17,7,18,18,7,8,1,12,0,12,16,17,15,1,2,15,12,1,15,14,12,14,16,12,14,13,16,2,3,15,3,11,15,4,10,3,3,10,11,4,5,10,11,14,15,11,10,14,10,9,14,10,5,9,9,5,13,9,13,14,13,5,6,13,6,16],"vertices":[2,5,82.02999877929688,6.829999923706055,0.25,6,35.09000015258789,-16.1200008392334,0.75,3,4,51.40999984741211,-111.51000213623047,0.10000000149011612,5,55.27000045776367,-32.43000030517578,0.44999998807907104,6,-9.3100004196167,-33.040000915527344,0.44999998807907104,3,4,30.329999923706055,-111.27999877929688,0.10000000149011612,5,43.400001525878906,-49.849998474121094,0.44999998807907104,6,-29.010000228881836,-40.540000915527344,0.44999998807907104,1,4,31.020000457763672,-47.900001525878906,1,1,4,31.280000686645508,-24.290000915527344,1,1,4,53.84000015258789,-24.530000686645508,1,1,4,134.27000427246094,-25.40999984741211,1,2,5,88.23999786376953,44.22999954223633,0.10000000149011612,6,61.560001373291016,11,0.8999999761581421,2,5,101.4000015258789,35.2599983215332,0.10000000149011612,6,67.2300033569336,-3.869999885559082,0.8999999761581421,1,4,59.560001373291016,-48.90999984741211,1,1,4,48.4900016784668,-47.380001068115234,1,1,4,44.5099983215332,-57.369998931884766,1,3,4,72.47000122070312,-85.5999984741211,0.10000000149011612,5,45.369998931884766,-0.550000011920929,0.44999998807907104,6,0.7799999713897705,-1.2100000381469727,0.44999998807907104,2,4,78.41000366210938,-57.150001525878906,0.30000001192092896,5,24.979999542236328,20.149999618530273,0.699999988079071,2,4,62.20000076293945,-69.23999786376953,0.30000001192092896,5,26.059999465942383,-0.029999999329447746,0.699999988079071,2,4,37.810001373291016,-83.98999786376953,0.30000001192092896,5,24.81999969482422,-28.510000228881836,0.699999988079071,3,4,91.25,-73.4800033569336,0.10000000149011612,5,45.689998626708984,21.799999237060547,0.44999998807907104,6,13.829999923706055,16.93000030517578,0.44999998807907104,2,5,65.80999755859375,27.260000228881836,0.25,6,33.45000076293945,9.899999618530273,0.75,2,5,74.91000366210938,14.670000076293945,0.25,6,33.720001220703125,-5.619999885559082,0.75],"hull":9}},"5c1cd0":{"5c1cd0":{"type":"region","name":"jianjia","path":"jianjia","rotation":38.9909782409668,"x":10.385250091552734,"y":6.8055572509765625,"scaleX":1,"scaleY":1,"width":55,"height":65,"color":"ffffffff"}}}},"skinsName":["default"],"events":{},"eventsName":[],"animations":{"idle":{"slots":{"7ca6ef":{"color":[{"time":0,"color":"ffffffff"}],"attachment":[{"time":0,"name":"7ca6ef"}]},"57fa1c":{"color":[{"time":0,"color":"ffffffff"}],"attachment":[{"time":0,"name":"57fa1c"}]},"88215a":{"color":[{"time":0,"color":"ffffffff"}],"attachment":[{"time":0,"name":"88215a"}]},"fa9d83":{"color":[{"time":0,"color":"ffffffff"}],"attachment":[{"time":0,"name":"fa9d83"}]},"8ebf44":{"color":[{"time":0,"color":"ffffffff"}],"attachment":[{"time":0,"name":"8ebf44"}]},"5c1cd0":{"color":[{"time":0,"color":"ffffffff"}],"attachment":[{"time":0,"name":"5c1cd0"}]},"bf50d4":{"color":[{"time":0,"color":"ffffffff"}],"attachment":[{"time":0,"name":"bf50d4"}]},"94afbe":{"color":[{"time":0,"color":"ffffffff"}],"attachment":[{"time":0,"name":"94afbe"}]},"a5b1a7":{"color":[{"time":0,"color":"ffffffff"}],"attachment":[{"time":0,"name":"a5b1a7"}]},"3311ec":{"color":[{"time":0,"color":"ffffffff"}],"attachment":[{"time":0,"name":"3311ec"}]},"ae4102":{"color":[{"time":0,"color":"ffffffff"}],"attachment":[{"time":0,"name":"ae4102"}]},"1125a9":{"color":[{"time":0,"color":"ffffffff"}],"attachment":[{"time":0,"name":"1125a9"}]},"4cda6e":{"color":[{"time":0,"color":"ffffffff"}],"attachment":[{"time":0,"name":"4cda6e"}]},"f8cef7":{"color":[{"time":0,"color":"ffffffff"}],"attachment":[{"time":0,"name":"f8cef7"}]},"c4dfa4":{"color":[{"time":0,"color":"ffffffff"}],"attachment":[{"time":0,"name":"c4dfa4"}]}},"bones":{"57fa1c":{"rotate":[{"time":0,"angle":0,"curve":"stepped"},{"time":0.5,"angle":0,"curve":"stepped"},{"time":1,"angle":0}],"translate":[{"time":0,"x":0,"y":0,"curve":[0.25,0,0.75,1]},{"time":0.5,"x":-2.1780166625976562,"y":-2.4200096130371094,"curve":[0.25,0,0.75,1]},{"time":1,"x":0,"y":0}],"scale":[{"time":0,"x":1,"y":1,"curve":"stepped"},{"time":1,"x":1,"y":1}]},"ae4102":{"rotate":[{"time":0,"angle":0,"curve":[0.25,0,0.75,1]},{"time":0.5,"angle":0.7047271728515625,"curve":[0.25,0,0.75,1]},{"time":1,"angle":0}],"translate":[{"time":0,"x":0,"y":0,"curve":"stepped"},{"time":0.5,"x":0,"y":0,"curve":"stepped"},{"time":1,"x":0,"y":0}],"scale":[{"time":0,"x":1,"y":1,"curve":"stepped"},{"time":1,"x":1,"y":1}]},"94afbe":{"rotate":[{"time":0,"angle":0,"curve":[0.25,0,0.75,1]},{"time":0.5,"angle":3.266566276550293,"curve":[0.25,0,0.75,1]},{"time":1,"angle":0}],"translate":[{"time":0,"x":0,"y":0,"curve":"stepped"},{"time":0.5,"x":0,"y":0,"curve":"stepped"},{"time":1,"x":0,"y":0}],"scale":[{"time":0,"x":1,"y":1,"curve":"stepped"},{"time":1,"x":1,"y":1}]},"bf50d4":{"rotate":[{"time":0,"angle":0,"curve":[0.1629612147808075,0.20328542590141296,0.75,1]},{"time":0.23333333432674408,"angle":-4.138622283935547,"curve":[0.25,0,0.75,1]},{"time":0.7666666507720947,"angle":3.9321060180664062,"curve":[0.25,0,0.8370388150215149,0.7967146039009094]},{"time":1,"angle":0}],"translate":[{"time":0,"x":0,"y":0,"curve":"stepped"},{"time":1,"x":0,"y":0}],"scale":[{"time":0,"x":1,"y":1,"curve":"stepped"},{"time":1,"x":1,"y":1}]},"88215a":{"rotate":[{"time":0,"angle":0,"curve":[0.25,0,0.75,1]},{"time":0.5,"angle":-10.82154655456543,"curve":[0.25,0,0.75,1]},{"time":1,"angle":0}],"translate":[{"time":0,"x":0,"y":0,"curve":"stepped"},{"time":1,"x":0,"y":0}],"scale":[{"time":0,"x":1,"y":1,"curve":"stepped"},{"time":1,"x":1,"y":1}]},"3311ec":{"rotate":[{"time":0,"angle":0,"curve":[0.1629612147808075,0.20328542590141296,0.75,1]},{"time":0.23333333432674408,"angle":2.9888381958007812,"curve":[0.25,0,0.75,1]},{"time":0.7666666507720947,"angle":-3.0293655395507812,"curve":[0.25,0,0.8370388150215149,0.7967146039009094]},{"time":1,"angle":0}],"translate":[{"time":0,"x":0,"y":0,"curve":"stepped"},{"time":1,"x":0,"y":0}],"scale":[{"time":0,"x":1,"y":1,"curve":"stepped"},{"time":1,"x":1,"y":1}]},"a5b1a7":{"rotate":[{"time":0,"angle":0,"curve":[0.25,0,0.75,1]},{"time":0.5,"angle":5.7001190185546875,"curve":[0.25,0,0.75,1]},{"time":1,"angle":0}],"translate":[{"time":0,"x":0,"y":0,"curve":"stepped"},{"time":0.5,"x":0,"y":0,"curve":"stepped"},{"time":1,"x":0,"y":0}],"scale":[{"time":0,"x":1,"y":1,"curve":"stepped"},{"time":1,"x":1,"y":1}]},"fa9d83":{"rotate":[{"time":0,"angle":0,"curve":[0.1629612147808075,0.20328542590141296,0.75,1]},{"time":0.23333333432674408,"angle":-2.028367042541504,"curve":[0.25,0,0.75,1]},{"time":0.7666666507720947,"angle":2.50601863861084,"curve":[0.25,0,0.8370388150215149,0.7967146039009094]},{"time":1,"angle":0}],"translate":[{"time":0,"x":0,"y":0,"curve":"stepped"},{"time":1,"x":0,"y":0}],"scale":[{"time":0,"x":1,"y":1,"curve":"stepped"},{"time":1,"x":1,"y":1}]},"c4dfa4":{"rotate":[{"time":0,"angle":0,"curve":[0.25,0,0.75,1]},{"time":0.5,"angle":-2.6629199981689453,"curve":[0.25,0,0.75,1]},{"time":1,"angle":0}],"translate":[{"time":0,"x":0,"y":0,"curve":"stepped"},{"time":0.5,"x":0,"y":0,"curve":"stepped"},{"time":1,"x":0,"y":0}],"scale":[{"time":0,"x":1,"y":1,"curve":"stepped"},{"time":1,"x":1,"y":1}]},"4cda6e":{"rotate":[{"time":0,"angle":0,"curve":[0.25,0,0.75,1]},{"time":0.5,"angle":-3.81298828125,"curve":[0.25,0,0.75,1]},{"time":1,"angle":0}],"translate":[{"time":0,"x":0,"y":0,"curve":"stepped"},{"time":0.5,"x":0,"y":0,"curve":"stepped"},{"time":1,"x":0,"y":0}],"scale":[{"time":0,"x":1,"y":1,"curve":"stepped"},{"time":1,"x":1,"y":1}]},"8ebf44":{"rotate":[{"time":0,"angle":0,"curve":[0.1629612147808075,0.20328542590141296,0.75,1]},{"time":0.23333333432674408,"angle":1.703059196472168,"curve":[0.25,0,0.75,1]},{"time":0.7666666507720947,"angle":-4.7985124588012695,"curve":[0.25,0,0.8370388150215149,0.7967146039009094]},{"time":1,"angle":0}],"translate":[{"time":0,"x":0,"y":0,"curve":"stepped"},{"time":1,"x":0,"y":0}],"scale":[{"time":0,"x":1,"y":1,"curve":"stepped"},{"time":1,"x":1,"y":1}]},"1125a9":{"rotate":[{"time":0,"angle":0,"curve":[0.25,0,0.75,1]},{"time":0.5,"angle":2.8621878623962402,"curve":[0.25,0,0.75,1]},{"time":1,"angle":0}],"translate":[{"time":0,"x":0,"y":0,"curve":"stepped"},{"time":0.5,"x":0,"y":0,"curve":"stepped"},{"time":1,"x":0,"y":0}],"scale":[{"time":0,"x":1,"y":1,"curve":"stepped"},{"time":1,"x":1,"y":1}]},"5c1cd0":{"rotate":[{"time":0,"angle":0,"curve":[0.1629612147808075,0.20328542590141296,0.75,1]},{"time":0.23333333432674408,"angle":-7.26654052734375,"curve":[0.25,0,0.75,1]},{"time":0.7666666507720947,"angle":7.7652740478515625,"curve":[0.25,0,0.8370388150215149,0.7967146039009094]},{"time":1,"angle":0}],"translate":[{"time":0,"x":0,"y":0,"curve":"stepped"},{"time":1,"x":0,"y":0}],"scale":[{"time":0,"x":1,"y":1,"curve":"stepped"},{"time":1,"x":1,"y":1}]},"935a6e":{"rotate":[{"time":0,"angle":0,"curve":[0.1629612147808075,0.20328542590141296,0.75,1]},{"time":0.23333333432674408,"angle":7.570892333984375,"curve":[0.25,0,0.75,1]},{"time":0.7666666507720947,"angle":-2.9960670471191406,"curve":[0.25,0,0.8370388150215149,0.7967146039009094]},{"time":1,"angle":0}],"translate":[{"time":0,"x":0,"y":0,"curve":"stepped"},{"time":1,"x":0,"y":0}],"scale":[{"time":0,"x":1,"y":1,"curve":"stepped"},{"time":1,"x":1,"y":1}]},"60947e":{"rotate":[{"time":0,"angle":0,"curve":[0.25,0,0.75,1]},{"time":0.5,"angle":-9.121742248535156,"curve":[0.25,0,0.75,1]},{"time":1,"angle":0}],"translate":[{"time":0,"x":0,"y":0,"curve":[0.25,0,0.75,1]},{"time":0.5,"x":1.9919891357421875,"y":0.8300018310546875,"curve":[0.25,0,0.75,1]},{"time":1,"x":0,"y":0}],"scale":[{"time":0,"x":1,"y":1,"curve":"stepped"},{"time":1,"x":1,"y":1}]},"f5980f":{"rotate":[{"time":0,"angle":0,"curve":[0.25,0,0.75,1]},{"time":0.5,"angle":18.542076110839844,"curve":[0.25,0,0.75,1]},{"time":1,"angle":0}],"translate":[{"time":0,"x":0,"y":0,"curve":"stepped"},{"time":0.5,"x":0,"y":0,"curve":"stepped"},{"time":1,"x":0,"y":0}],"scale":[{"time":0,"x":1,"y":1,"curve":"stepped"},{"time":1,"x":1,"y":1}]},"6ff11b":{"rotate":[{"time":0,"angle":0,"curve":[0.25,0,0.75,1]},{"time":0.5,"angle":4.8269805908203125,"curve":[0.25,0,0.75,1]},{"time":1,"angle":0}],"translate":[{"time":0,"x":0,"y":0,"curve":[0.25,0,0.75,1]},{"time":0.5,"x":-2.4900054931640625,"y":-3.0517578125e-5,"curve":[0.25,0,0.75,1]},{"time":1,"x":0,"y":0}],"scale":[{"time":0,"x":1,"y":1,"curve":"stepped"},{"time":1,"x":1,"y":1}]},"3f68db":{"rotate":[{"time":0,"angle":0,"curve":"stepped"},{"time":0.5,"angle":0,"curve":"stepped"},{"time":1,"angle":0}],"translate":[{"time":0,"x":0,"y":0,"curve":"stepped"},{"time":0.5,"x":0,"y":0,"curve":"stepped"},{"time":1,"x":0,"y":0}],"scale":[{"time":0,"x":1,"y":1,"curve":"stepped"},{"time":1,"x":1,"y":1}]},"62d472":{"rotate":[{"time":0,"angle":0,"curve":"stepped"},{"time":0.5,"angle":0,"curve":"stepped"},{"time":1,"angle":0}],"translate":[{"time":0,"x":0,"y":0,"curve":"stepped"},{"time":0.5,"x":0,"y":0,"curve":"stepped"},{"time":1,"x":0,"y":0}],"scale":[{"time":0,"x":1,"y":1,"curve":"stepped"},{"time":1,"x":1,"y":1}]},"f64a7c":{"rotate":[{"time":0,"angle":0,"curve":"stepped"},{"time":0.5,"angle":0,"curve":"stepped"},{"time":1,"angle":0}],"translate":[{"time":0,"x":0,"y":0,"curve":"stepped"},{"time":0.5,"x":0,"y":0,"curve":"stepped"},{"time":1,"x":0,"y":0}],"scale":[{"time":0,"x":1,"y":1,"curve":"stepped"},{"time":1,"x":1,"y":1}]},"dc37a6":{"rotate":[{"time":0,"angle":0,"curve":[0.1629612147808075,0.20328542590141296,0.75,1]},{"time":0.23333333432674408,"angle":4.0728302001953125,"curve":[0.25,0,0.75,1]},{"time":0.7666666507720947,"angle":-2.9254913330078125,"curve":[0.25,0,0.8370388150215149,0.7967146039009094]},{"time":1,"angle":0}],"translate":[{"time":0,"x":0,"y":0,"curve":"stepped"},{"time":1,"x":0,"y":0}],"scale":[{"time":0,"x":1,"y":1,"curve":"stepped"},{"time":1,"x":1,"y":1}]},"c8103c":{"rotate":[{"time":0,"angle":0,"curve":[0.25,0,0.75,1]},{"time":0.5,"angle":9.045134544372559,"curve":[0.25,0,0.75,1]},{"time":1,"angle":0}],"translate":[{"time":0,"x":0,"y":0,"curve":"stepped"},{"time":1,"x":0,"y":0}],"scale":[{"time":0,"x":1,"y":1,"curve":"stepped"},{"time":1,"x":1,"y":1}]},"c927d8":{"rotate":[{"time":0,"angle":0,"curve":[0.1629612147808075,0.20328542590141296,0.75,1]},{"time":0.23333333432674408,"angle":-10.115943908691406,"curve":[0.25,0,0.75,1]},{"time":0.7666666507720947,"angle":12.668327331542969,"curve":[0.25,0,0.8370388150215149,0.7967146039009094]},{"time":1,"angle":0}],"translate":[{"time":0,"x":0,"y":0,"curve":"stepped"},{"time":1,"x":0,"y":0}],"scale":[{"time":0,"x":1,"y":1,"curve":"stepped"},{"time":1,"x":1,"y":1}]},"d8742a":{"rotate":[{"time":0,"angle":0,"curve":"stepped"},{"time":1,"angle":0}],"translate":[{"time":0,"x":0,"y":0,"curve":"stepped"},{"time":1,"x":0,"y":0}],"scale":[{"time":0,"x":1,"y":1},{"time":0.5,"x":0.8999999761581421,"y":1},{"time":1,"x":1,"y":1}]}},"deform":{"default":{"57fa1c":{"57fa1c":[{"time":0}]},"88215a":{"88215a":[{"time":0}]},"8ebf44":{"8ebf44":[{"time":0}]},"ae4102":{"ae4102":[{"time":0}]},"1125a9":{"1125a9":[{"time":0}]}}},"drawOrder":[{"time":0,"offsets":[]}]}}}